<?xml version="1.0" encoding="UTF-8"?>
<metadata xml:lang="en"><Esri><CreaDate>20200425</CreaDate><CreaTime>16202800</CreaTime><ArcGISFormat>1.0</ArcGISFormat><SyncOnce>TRUE</SyncOnce><DataProperties><lineage><Process ToolSource="c:\program files\arcgis\pro\Resources\ArcToolbox\toolboxes\Conversion Tools.tbx\RasterToASCII" Date="20200425" Time="162028">RasterToASCII ..\input/Land_use_Soils_data\CanCovRas ..\input\Land_use_Soils_data\CanCovRas.asc</Process><Process ToolSource="c:\program files\arcgis\pro\Resources\ArcToolbox\toolboxes\Conversion Tools.tbx\RasterToASCII" Date="20200425" Time="162046">RasterToASCII ..\input/Land_use_Soils_data\CanCovRas ..\input\Land_use_Soils_data\CanCovRas.asc</Process><Process ToolSource="c:\program files\arcgis\pro\Resources\ArcToolbox\toolboxes\Conversion Tools.tbx\RasterToASCII" Date="20200426" Time="213928">RasterToASCII ..\input/Land_use_Soils_data\CanCovRas ..\input\Land_use_Soils_data\CanCovRas.asc</Process><Process ToolSource="c:\program files\arcgis\pro\Resources\ArcToolbox\toolboxes\Conversion Tools.tbx\RasterToASCII" Date="20200426" Time="213953">RasterToASCII ..\input/Land_use_Soils_data\CanCovRas ..\input\Land_use_Soils_data\CanCovRas.asc</Process></lineage></DataProperties></Esri></metadata>
